README.md
setup.py
oif/__init__.py
oif/__main__.py
oif/_version.py
oif/dbg.py
oif/ooephemerides.py
oif/orbits.py
oif/shared.py
oif/sso.py
oif/telescope.py
oif.egg-info/PKG-INFO
oif.egg-info/SOURCES.txt
oif.egg-info/dependency_links.txt
oif.egg-info/entry_points.txt
oif.egg-info/not-zip-safe
oif.egg-info/requires.txt
oif.egg-info/top_level.txt