Metadata-Version: 2.1
Name: oif
Version: 0.0.0
Summary: A package to efficiently tell whether a set of objects are in field
Home-page: http://github.com/AsteroidSurveySimulator/objectsInField
Author: Shantanu Naidu and the OIF Team
Author-email: shantanu.p.naidu@jpl.nasa.gov
License: BSD 3-Clause
Platform: UNKNOWN
Classifier: Development Status :: 2 - Pre-Alpha
Classifier: Programming Language :: Python
Classifier: Programming Language :: Python :: 3
Classifier: Intended Audience :: Science/Research
Classifier: Intended Audience :: Developers
Classifier: Natural Language :: English
Classifier: Topic :: Scientific/Engineering
Classifier: Topic :: Scientific/Engineering :: Astronomy
Classifier: Topic :: Scientific/Engineering :: Physics
Classifier: Operating System :: POSIX
Classifier: Operating System :: Unix
Classifier: Operating System :: MacOS
Classifier: License :: OSI Approved :: BSD License
Requires-Python: >=3.6.*
Provides-Extra: dev
Provides-Extra: docs
